sofa/__init__.py
sofa/models/SOFA.py
sofa/plots/__init__.py
sofa/plots/plots.py
sofa/utils/__init__.py
sofa/utils/utils.py
biosofa-0.7.5.dist-info/LICENSE
biosofa-0.7.5.dist-info/METADATA
biosofa-0.7.5.dist-info/WHEEL
biosofa-0.7.5.dist-info/RECORD
