Metadata-Version: 2.1
Name: biosofa
Version: 0.7.5
Summary: Probabilistic factor analysis model with covariate guided factors
License: MIT
Author: capraz
Author-email: tuemayc@hotmail.com
Requires-Python: >=3.8.1,<3.11.6
Classifier: License :: OSI Approved :: MIT License
Classifier: Programming Language :: Python :: 3
Classifier: Programming Language :: Python :: 3.9
Classifier: Programming Language :: Python :: 3.10
Classifier: Programming Language :: Python :: 3.11
Provides-Extra: docs
Provides-Extra: notebook
Requires-Dist: Sphinx (==4.2.0) ; extra == "docs"
Requires-Dist: click (>=8.1.3)
Requires-Dist: gseapy (>=1.0.4)
Requires-Dist: jupyter ; extra == "notebook"
Requires-Dist: matplotlib (>=3.5.2)
Requires-Dist: muon (>=0.1.3)
Requires-Dist: nbsphinx (==0.8.9) ; extra == "docs"
Requires-Dist: numba (>=0.55.2)
Requires-Dist: numpy (>=1.22.4)
Requires-Dist: pandas (>=1.4.2)
Requires-Dist: pyro-ppl (<1.8.4)
Requires-Dist: pytest
Requires-Dist: scikit-learn (>=1.1.1)
Requires-Dist: scipy (>=1.8.1)
Requires-Dist: sphinx-rtd-theme (==1.0.0) ; extra == "docs"
Requires-Dist: sphinxcontrib-bibtex (>=2.5.0,<3.0.0)
Requires-Dist: sphinxcontrib-napoleon (==0.7) ; extra == "docs"
Requires-Dist: toml (>=0.10.2)
Requires-Dist: torch (>=1.13.1,<2.0.0)
